botrun_log/__init__.py
botrun_log/crypto_manager.py
botrun_log/database_manager.py
botrun_log/etl_manager.py
botrun_log/log_entry.py
botrun_log/logger.py
botrun_log-0.10.0.dist-info/METADATA
botrun_log-0.10.0.dist-info/WHEEL
botrun_log-0.10.0.dist-info/RECORD
