Metadata-Version: 2.4
Name: botrun-log
Version: 0.10.0
Summary: A Python package for botrun-application logging, using Google BigQuery and PostgreSQL.
Project-URL: Homepage, https://github.com/bohachu/bigquery_log_jc
Author-email: JcXGTcW <jcxgtcw@gmail.com>
License: MIT
Classifier: License :: OSI Approved :: MIT License
Classifier: Operating System :: OS Independent
Classifier: Programming Language :: Python :: 3.8
Requires-Python: >=3.11
Requires-Dist: cryptography
Requires-Dist: google-auth
Requires-Dist: google-cloud-bigquery
Requires-Dist: psycopg2-binary
Requires-Dist: python-dotenv
Requires-Dist: pytz
Provides-Extra: dev
Requires-Dist: build>=1.2.2; extra == 'dev'
Requires-Dist: pytest; extra == 'dev'
Requires-Dist: twine>=5.1.1; extra == 'dev'
